.bumpversion.cfg
.coveragerc
.gitignore
CONTRIBUTING.rst
HISTORY.rst
LICENSE
MANIFEST.in
Makefile
README.rst
runtests.sh
setup.cfg
setup.py
uncythonize.py
tests/mlfriends.pyx
tests/stepfuncs.pyx
uncythonize.egg-info/PKG-INFO
uncythonize.egg-info/SOURCES.txt
uncythonize.egg-info/dependency_links.txt
uncythonize.egg-info/top_level.txt