Metadata-Version: 1.2
Name: uncythonize
Version: 0.1.1
Summary: Strips cython code (.pyx files) down to python code for code analysis tools.
Home-page: https://github.com/JohannesBuchner/uncythonize
Author: Johannes Buchner
Author-email: johannes.buchner.acad@gmx.com
License: GPL-3
Platform: UNKNOWN
Classifier: Development Status :: 2 - Pre-Alpha
Classifier: Intended Audience :: Developers
Classifier: License :: OSI Approved :: GNU General Public License v3 (GPLv3)
Classifier: Natural Language :: English
Classifier: Programming Language :: Python :: 3
Classifier: Programming Language :: Python :: 3.5
Classifier: Programming Language :: Python :: 3.6
Classifier: Programming Language :: Python :: 3.7
Classifier: Programming Language :: Python :: 3.8
Requires-Python: >=3.5
